hust_login/_HustPass.py
hust_login/__init__.py
hust_login/__main__.py
hust_login/_cli.py
hust_login/autotest.py
hust_login/curriculum.py
hust_login/decaptcha.py
hust_login/ecard_bills.py
hust_login/free_room.py
hust_login/login.py
hust_login/utility_bills.py
hust_login-2.0.0.dist-info/LICENSE
hust_login-2.0.0.dist-info/METADATA
hust_login-2.0.0.dist-info/WHEEL
hust_login-2.0.0.dist-info/top_level.txt
hust_login-2.0.0.dist-info/RECORD
