Metadata-Version: 2.1
Name: hust-login
Version: 2.0.0
Summary: A python-lib for authenticating HustPass@2023
Home-page: https://github.com/MarvinTerry/HustLogin
Author: MarvinTerry
Author-email: marvinterry2004@gmail.com
Maintainer: Jackhr-arch
Maintainer-email: 63526062+Jackhr-arch@users.noreply.github.com
License: MIT
Classifier: Programming Language :: Python :: 3
Classifier: License :: OSI Approved :: MIT License
Classifier: Operating System :: OS Independent
License-File: LICENSE
Requires-Dist: Pillow >=10.0.0
Requires-Dist: pycryptodome >=3.18.0
Requires-Dist: pytesseract >=0.3.10
Requires-Dist: Requests >=2.31.0
